{
    "chainid": 421614,
    "description": "deploy a new delayed oracle",
    "network": "sepolia",
    "proposalType": "DeployDelayedOracles",
    "ODGovernor_Address": "",
    "DelayedOracleFactory_Address": "",
    "objectArray": [
        {
            "symbol": "LINK/USD",
            "chainlinkPriceFeed": "0x86E53CF1B870786351Da77A57575e79CB55812CB",
            "interval": "86400"
        },
        {
            "symbol": "GRT/USD",
            "chainlinkPriceFeed": "0x0F38D86FceF4955B705F35c9e41d1A16e0637c73",
            "interval": "86400"
        },
        {
            "symbol": "ETH/USD",
            "chainlinkPriceFeed": "0x639Fe6ab55C921f74e7fac1ee960C0B6293ba612",
            "interval": "86400"
        }
    ],
    "arrayLength": "3"
}